[
    {
        "base_currency": "PLN",
        "target_currency": "EUR",
        "date_fetched": "2023-03-10",
        "ratio": 0.213378
    },
    {
        "base_currency": "PLN",
        "target_currency": "USD",
        "date_fetched": "2023-03-10",
        "ratio": 0.225931
    },
    {
        "base_currency": "USD",
        "target_currency": "EUR",
        "date_fetched": "2023-03-10",
        "ratio": 0.944437
    },
    {
        "base_currency": "USD",
        "target_currency": "PLN",
        "ratio": 4.426129,
        "date_fetched": "2023-03-10"
    }
]